topology_radiomics/__init__.py
topology_radiomics/config.py
topology_radiomics/morphology_features.py
topology_radiomics/reporting.py
topology_radiomics/sanitization.py
topology_radiomics-0.0.1.dist-info/METADATA
topology_radiomics-0.0.1.dist-info/WHEEL
topology_radiomics-0.0.1.dist-info/top_level.txt
topology_radiomics-0.0.1.dist-info/RECORD
