Metadata-Version: 2.1
Name: topology-radiomics
Version: 0.0.1
Summary: Topology Radiomics by INVENT and BRIC lab
Home-page: https://github.com/Toth-Technology/bric-morphology
Author: Toth Technology
Author-email: toth-tech@hillyer.me
License: UNKNOWN
Project-URL: Github, https://github.com/Toth-Technology/bric-morphology
Keywords: Topology Radiomics
Platform: UNKNOWN
Classifier: Development Status :: 3 - Alpha
Classifier: Intended Audience :: Science/Research
Classifier: Intended Audience :: Developers
Classifier: License :: OSI Approved :: BSD License
Classifier: Operating System :: OS Independent
Classifier: Operating System :: POSIX :: Linux
Classifier: Operating System :: Microsoft :: Windows :: Windows 10
Classifier: Operating System :: MacOS
Classifier: Programming Language :: Python :: 3
Classifier: Topic :: Scientific/Engineering :: Bio-Informatics
Requires-Python: >=3.6
Requires-Dist: numpy
Requires-Dist: scikit-image
Requires-Dist: pyvista
Requires-Dist: pandas
Requires-Dist: sphinx
